{"cameraMode":{"drawMode":0,"name":"Shaded","section":"Shading Mode"},"sceneLighting":false,"audioPlay":false,"sceneViewState":{"m_AlwaysRefresh":false,"showFog":true,"showSkybox":false,"showFlares":true,"showImageEffects":true,"showParticleSystems":true,"showVisualEffectGraphs":true,"m_FxEnabled":true},"in2DMode":false,"pivot":{"x":6.349166393280029,"y":-1.784192681312561,"z":-3.538231611251831},"rotation":{"x":0.10976802557706833,"y":0.6182298064231873,"z":-0.0877528041601181,"w":0.7733304500579834},"size":4.046131610870361,"orthographic":false}